MANIFEST.in
README.rst
setup.py
docs/Makefile
docs/conf.py
docs/index.rst
docs/_build/html/_images/02_email_message_template.png
docs/_build/html/_images/03_basic_setup.png
docs/_build/html/_images/04_add_step.png
docs/_build/html/_images/05_set_script.png
docs/_build/html/_images/06_open_task_scheduler.png
docs/_build/html/_images/07_create_task.png
docs/_build/html/_images/08_edit_trigger.png
docs/_build/html/_images/09_edit_action.png
docs/_build/html/_images/10_task_settings.png
docs/_build/html/_static/comment-bright.png
docs/_build/html/_static/comment-close.png
docs/_build/html/_static/comment.png
docs/_build/html/_static/down-pressed.png
docs/_build/html/_static/down.png
docs/_build/html/_static/file.png
docs/_build/html/_static/minus.png
docs/_build/html/_static/plus.png
docs/_build/html/_static/up-pressed.png
docs/_build/html/_static/up.png
docs/images/psched/02_email_message_template.png
docs/images/psched/03_basic_setup.png
docs/images/psched/04_add_step.png
docs/images/psched/05_set_script.png
docs/images/psched/06_open_task_scheduler.png
docs/images/psched/07_create_task.png
docs/images/psched/08_edit_trigger.png
docs/images/psched/09_edit_action.png
docs/images/psched/10_task_settings.png
docs/images/psched/11_task_summary.png
docs/src/customize_a_form.rst
docs/src/form_client.rst
docs/src/leisurelystart.rst
docs/src/poller.rst
docs/src/quickstart.rst
docs/src/workflow.rst
docs/src/workflow/send_approval_form_email.rst
docs/src/workflow/send_credit_limit_approval_form_email.rst
poplar_forms/__init__.py
poplar_forms/expi.json
poplar_forms/form_client.py
poplar_forms.egg-info/PKG-INFO
poplar_forms.egg-info/SOURCES.txt
poplar_forms.egg-info/dependency_links.txt
poplar_forms.egg-info/top_level.txt
poplar_forms/PPFORMS/__init__.py
poplar_forms/PPFORMS/scripts/__init__.py
poplar_forms/PPFORMS/scripts/poller.py
poplar_forms/PPFORMS/scripts/remote_approvals.py
poplar_forms/PPFORMS/workflow/SendApprovalFormEmail.py
poplar_forms/PPFORMS/workflow/SendCreditLimitApprovalFormEmail.py
poplar_forms/PPFORMS/workflow/__init__.py
poplar_forms/vi/PPFORMS.poplar.vi